{
  "version": "https://jsonfeed.org/version/1",
  "title": "Colorado Attorneys Against Police Violence",
  "home_page_url": "https://www.facebook.com/Colorado-Attorneys-Against-Police-Violence-106087521153591/?fref=tag",
  "description": "Posts from Colorado Attorneys Against Police Violence",
  "author": {
    "name": "Colorado Attorneys Against Police Violence"
  },
  "items": [
    {
      "id": "https://www.facebook.com/106087521153591/photos/a.106389027790107/204279538001055/",
      "url": "https://www.facebook.com/106087521153591/photos/a.106389027790107/204279538001055/",
      "title": "one police murder is too many. may we all work to create a world...",
      "content_html": "\u003ca href=\"https://www.facebook.com/Colorado-Attorneys-Against-Police-Violence-106087521153591/\"\u003e\u003cimg src=\"https://scontent.fapa1-1.fna.fbcdn.net/v/t1.0-1/cp0/c23.0.50.50a/p50x50/118569704_145892603839749_1971037107782593743_n.png?_nc_cat=108\u0026ccb=2\u0026_nc_sid=dbb9e7\u0026_nc_ohc=m3os2-uLM0MAX_OEXRa\u0026_nc_ht=scontent.fapa1-1.fna\u0026_nc_tp=30\u0026oh=052ffa638da2b30bbb6033dbbd5bec94\u0026oe=6013C7AF\" alt=\"\" /\u003e\u003c/a\u003e\u003ca href=\"https://www.facebook.com/Colorado-Attorneys-Against-Police-Violence-106087521153591/\"\u003eColorado Attorneys Against Police Violence\u003c/a\u003e\u003ca href=\"https://www.facebook.com/106087521153591/photos/a.106389027790107/204279538001055/\"\u003e\u003c/a\u003e\u003ci\u003e\u003c/i\u003e\u003cp\u003eone police murder is too many. may we all work to create a world where people are not hunted by those sworn to serve and protect. \u003ca href=\"https://www.facebook.com/hashtag/holdcopsaccountable\"\u003e#HoldCopsAccountable\u003c/a\u003e \u003ca href=\"https://www.facebook.com/hashtag/caapv\"\u003e#CAAPV\u003c/a\u003e\u003c/p\u003e\u003ca href=\"https://www.facebook.com/106087521153591/photos/a.106389027790107/204279538001055/\"\u003e\u003cimg src=\"https://scontent.fapa1-1.fna.fbcdn.net/v/t1.0-0/p526x296/135011416_204279541334388_5880664164437987921_o.jpg?_nc_cat=103\u0026ccb=2\u0026_nc_sid=8024bb\u0026_nc_ohc=lRtr2TJpoOoAX-a7UsH\u0026_nc_ht=scontent.fapa1-1.fna\u0026tp=6\u0026oh=21e899e3132e8c6e290f30056ea6de52\u0026oe=6016E810\" alt=\"Image may contain: text that says 'DID YOU KNOW: IN 2020, POLICE MURDERED 981 PEOPLE, INCLUDING THE 34 PEOPLE MURDERED BY COLORADO POLICE. FB Colorado Attorneys Against Police Violence \u0026#064;ColoradoAAPV :\u0026#064;caapv_ hello\u0026#064;caapv.org www.caapv.org L CAAPV'\" width=\"500\" height=\"889\" caption=\"Image may contain: text that says 'DID YOU KNOW: IN 2020, POLICE MURDERED 981 PEOPLE, INCLUDING THE 34 PEOPLE MURDERED BY COLORADO POLICE. FB Colorado Attorneys Against Police Violence \u0026#064;ColoradoAAPV :\u0026#064;caapv_ hello\u0026#064;caapv.org www.caapv.org L CAAPV'\" /\u003e\u003c/a\u003e",
      "date_published": "2021-01-01T10:56:00-07:00",
      "date_modified": "2021-01-01T10:56:00-07:00",
      "author": {
        "name": "Colorado Attorneys Against Police Violence"
      }
    },
    {
      "id": "https://www.facebook.com/202880948140914",
      "url": "https://www.facebook.com/202880948140914",
      "title": "...",
      "content_html": "\u003ca href=\"https://www.facebook.com/Colorado-Attorneys-Against-Police-Violence-106087521153591/\"\u003e\u003cimg src=\"https://scontent.fapa1-1.fna.fbcdn.net/v/t1.0-1/cp0/c23.0.50.50a/p50x50/118569704_145892603839749_1971037107782593743_n.png?_nc_cat=108\u0026ccb=2\u0026_nc_sid=dbb9e7\u0026_nc_ohc=m3os2-uLM0MAX_OEXRa\u0026_nc_ht=scontent.fapa1-1.fna\u0026_nc_tp=30\u0026oh=052ffa638da2b30bbb6033dbbd5bec94\u0026oe=6013C7AF\" alt=\"\" /\u003e\u003c/a\u003e\u003ca href=\"https://www.facebook.com/Colorado-Attorneys-Against-Police-Violence-106087521153591/\"\u003eColorado Attorneys Against Police Violence\u003c/a\u003e\u003ca href=\"https://www.facebook.com/permalink.php\"\u003e\u003c/a\u003e\u003ci\u003e\u003c/i\u003e\u003cp\u003e\u003ca href=\"https://www.cpr.org/2020/12/29/courts-cant-compel-polis-to-let-people-out-of-prison-judge-rules/?fbclid=IwAR2OZiG3oRAW4h4bIL0eC_VS7JraQfK8JDd5Rbdk66ZMscfkDL3Abrg_Ang\"\u003ehttps://www.cpr.org/…/courts-cant-compel-polis-to-let-peo…/…\u003c/a\u003e\u003c/p\u003e\u003ca href=\"https://www.cpr.org/2020/12/29/courts-cant-compel-polis-to-let-people-out-of-prison-judge-rules/\"\u003eThe ACLU of Colorado filed the suit, hoping the court would order Gov. Polis to exercise his executive authority and reduce the coronavirus risk in Colorado's prisons. But a judge rejected that argument.\u003cimg src=\"https://external.fapa1-1.fna.fbcdn.net/safe_image.php?d=AQGycG9fdeBJMqKt\u0026w=540\u0026h=282\u0026url=https%3A%2F%2Fwp-cpr.s3.amazonaws.com%2Fuploads%2F2020%2F11%2FAP20329855733162-scaled.jpg%3Fresize%3D1200%2C600\u0026cfs=1\u0026upscale=1\u0026fallback=news_d_placeholder_publisher\u0026_nc_cb=1\u0026_nc_hash=AQFrDGO80byopQic\" alt=\"\" width=\"500\" height=\"262\" caption=\"\" /\u003e\u003c/a\u003e\u003cp\u003ecpr.org\u003c/p\u003e\u003cp\u003eCourts Can’t Compel Polis To Let People Out Of Prison, Judge Rules\u003c/p\u003eThe ACLU of Colorado filed the suit, hoping the court would order Gov. Polis to exercise his executive authority and reduce the coronavirus risk in Colorado's prisons. But a judge rejected that argument.\u003ca href=\"https://www.cpr.org/2020/12/29/courts-cant-compel-polis-to-let-people-out-of-prison-judge-rules/\"\u003eThe ACLU of Colorado filed the suit, hoping the court would order Gov. Polis to exercise his executive authority and reduce the coronavirus risk in Colorado's prisons. But a judge rejected that argument.\u003c/a\u003e",
      "date_published": "2020-12-30T09:26:26-07:00",
      "date_modified": "2020-12-30T09:26:26-07:00",
      "author": {
        "name": "Colorado Attorneys Against Police Violence"
      }
    },
    {
      "id": "https://www.facebook.com/202279258201083",
      "url": "https://www.facebook.com/202279258201083",
      "title": "...",
      "content_html": "\u003ca href=\"https://www.facebook.com/Colorado-Attorneys-Against-Police-Violence-106087521153591/\"\u003e\u003cimg src=\"https://scontent.fapa1-1.fna.fbcdn.net/v/t1.0-1/cp0/c23.0.50.50a/p50x50/118569704_145892603839749_1971037107782593743_n.png?_nc_cat=108\u0026ccb=2\u0026_nc_sid=dbb9e7\u0026_nc_ohc=m3os2-uLM0MAX_OEXRa\u0026_nc_ht=scontent.fapa1-1.fna\u0026_nc_tp=30\u0026oh=052ffa638da2b30bbb6033dbbd5bec94\u0026oe=6013C7AF\" alt=\"\" /\u003e\u003c/a\u003e\u003ca href=\"https://www.facebook.com/Colorado-Attorneys-Against-Police-Violence-106087521153591/\"\u003eColorado Attorneys Against Police Violence\u003c/a\u003e\u003ca href=\"https://www.facebook.com/permalink.php\"\u003e\u003c/a\u003e\u003ci\u003e\u003c/i\u003e\u003cp\u003e\u003ca href=\"https://coloradosun.com/2020/12/28/coronavirus-prison-deaths-colorado-24/?fbclid=IwAR1yVeK23lXIIU8ZazfeTThlddXIcl0g_n54ObCt3sk2x_6e2rVyyaOz-pQ\"\u003ehttps://coloradosun.com/…/coronavirus-prison-deaths-color…/…\u003c/a\u003e\u003c/p\u003e\u003ca href=\"https://coloradosun.com/2020/12/28/coronavirus-prison-deaths-colorado-24/\"\u003eThe new fatalities come even as active coronavirus cases in Colorado Department of Corrections facilities are decreasing\u003cimg src=\"https://external.fapa1-1.fna.fbcdn.net/safe_image.php?d=AQHLPmqPuV45WyVz\u0026w=540\u0026h=282\u0026url=https%3A%2F%2Fcoloradosun.com%2Fwp-content%2Fuploads%2Fsites%2F15%2F2020%2F12%2FColo_Prison_Territorial.jpg%3Fresize%3D1200%2C630\u0026cfs=1\u0026upscale=1\u0026fallback=news_d_placeholder_publisher\u0026_nc_cb=1\u0026_nc_hash=AQEJW0e4CbEeXGic\" alt=\"\" width=\"500\" height=\"262\" caption=\"\" /\u003e\u003c/a\u003e\u003cp\u003ecoloradosun.com\u003c/p\u003e\u003cp\u003eFour more Colorado prisoners die after suspected coronavirus infections, bringing pandemic total to 24\u003c/p\u003eThe new fatalities come even as active coronavirus cases in Colorado Department of Corrections facilities are decreasing\u003ca href=\"https://coloradosun.com/2020/12/28/coronavirus-prison-deaths-colorado-24/\"\u003eThe new fatalities come even as active coronavirus cases in Colorado Department of Corrections facilities are decreasing\u003c/a\u003e",
      "date_published": "2020-12-29T10:45:01-07:00",
      "date_modified": "2020-12-29T10:45:01-07:00",
      "author": {
        "name": "Colorado Attorneys Against Police Violence"
      }
    },
    {
      "id": "https://www.facebook.com/202270861535256",
      "url": "https://www.facebook.com/202270861535256",
      "title": "we’ve said it before, and we’ll say it again: jails and...",
      "content_html": "\u003ca href=\"https://www.facebook.com/Colorado-Attorneys-Against-Police-Violence-106087521153591/\"\u003e\u003cimg src=\"https://scontent.fapa1-1.fna.fbcdn.net/v/t1.0-1/cp0/c23.0.50.50a/p50x50/118569704_145892603839749_1971037107782593743_n.png?_nc_cat=108\u0026ccb=2\u0026_nc_sid=dbb9e7\u0026_nc_ohc=m3os2-uLM0MAX_OEXRa\u0026_nc_ht=scontent.fapa1-1.fna\u0026_nc_tp=30\u0026oh=052ffa638da2b30bbb6033dbbd5bec94\u0026oe=6013C7AF\" alt=\"\" /\u003e\u003c/a\u003e\u003ca href=\"https://www.facebook.com/Colorado-Attorneys-Against-Police-Violence-106087521153591/\"\u003eColorado Attorneys Against Police Violence\u003c/a\u003e\u003ca href=\"https://www.facebook.com/permalink.php\"\u003e\u003c/a\u003e\u003ci\u003e\u003c/i\u003e\u003cp\u003ewe’ve said it before, and we’ll say it again: jails and prisons are a public health crisis. a jail or prison sentence should not be a death sentence. \u003c/p\u003e\u003cp\u003e \u003ca href=\"https://www.cpr.org/2020/12/28/as-gov-polis-and-prisoner-advocates-tangle-in-court-an-inmate-describes-dire-conditions-inside/?fbclid=IwAR1Vn0mgkF7FYm4r40GadHoz2_1kdjwlT6WBtVOIoBsO0AHoEm6OCrapYHU\"\u003ehttps://www.cpr.org/…/as-gov-polis-and-prisoner-advocates…/…\u003c/a\u003e\u003c/p\u003e\u003ca href=\"https://www.cpr.org/2020/12/28/as-gov-polis-and-prisoner-advocates-tangle-in-court-an-inmate-describes-dire-conditions-inside/\"\u003eAdvocates want Polis to let more people out, and speed up vaccinations for those who remain, to slow the spread of COVID-19 through Colorado's prisons.\u003cimg src=\"https://external.fapa1-1.fna.fbcdn.net/safe_image.php?d=AQEpVzjG0VrDIlvn\u0026w=540\u0026h=282\u0026url=https%3A%2F%2Fwp-cpr.s3.amazonaws.com%2Fuploads%2F2019%2F05%2Fcurtis-brooks5.jpg%3Fresize%3D1200%2C600\u0026cfs=1\u0026upscale=1\u0026fallback=news_d_placeholder_publisher\u0026_nc_cb=1\u0026_nc_hash=AQHH08hdLAZzeIq_\" alt=\"\" width=\"500\" height=\"262\" caption=\"\" /\u003e\u003c/a\u003e\u003cp\u003ecpr.org\u003c/p\u003e\u003cp\u003eAs Gov. Polis And Prisoner Advocates Tangle In Court, An Inmate Describes Dire Conditions Inside\u003c/p\u003eAdvocates want Polis to let more people out, and speed up vaccinations for those who remain, to slow the spread of COVID-19 through Colorado's prisons.\u003ca href=\"https://www.cpr.org/2020/12/28/as-gov-polis-and-prisoner-advocates-tangle-in-court-an-inmate-describes-dire-conditions-inside/\"\u003eAdvocates want Polis to let more people out, and speed up vaccinations for those who remain, to slow the spread of COVID-19 through Colorado's prisons.\u003c/a\u003e",
      "date_published": "2020-12-29T10:26:24-07:00",
      "date_modified": "2020-12-29T10:26:24-07:00",
      "author": {
        "name": "Colorado Attorneys Against Police Violence"
      }
    },
    {
      "id": "https://www.facebook.com/198536241908718",
      "url": "https://www.facebook.com/198536241908718",
      "title": "redemption is real. ...",
      "content_html": "\u003ca href=\"https://www.facebook.com/Colorado-Attorneys-Against-Police-Violence-106087521153591/\"\u003e\u003cimg src=\"https://scontent.fapa1-1.fna.fbcdn.net/v/t1.0-1/cp0/c23.0.50.50a/p50x50/118569704_145892603839749_1971037107782593743_n.png?_nc_cat=108\u0026ccb=2\u0026_nc_sid=dbb9e7\u0026_nc_ohc=m3os2-uLM0MAX_OEXRa\u0026_nc_ht=scontent.fapa1-1.fna\u0026_nc_tp=30\u0026oh=052ffa638da2b30bbb6033dbbd5bec94\u0026oe=6013C7AF\" alt=\"\" /\u003e\u003c/a\u003e\u003ca href=\"https://www.facebook.com/Colorado-Attorneys-Against-Police-Violence-106087521153591/\"\u003eColorado Attorneys Against Police Violence\u003c/a\u003e\u003ca href=\"https://www.facebook.com/permalink.php\"\u003e\u003c/a\u003e\u003ci\u003e\u003c/i\u003e\u003cp\u003eredemption is real. \u003c/p\u003e\u003cp\u003e \u003ca href=\"https://denvergazette.com/news/local/sentence-reduced-for-abused-teen-who-got-life-for-killing-denver-police-officer-in-1995/article_a5ef2dee-9577-5222-90ad-f3eefd8dacc9.html?utm_medium=social\u0026utm_source=facebook\u0026utm_campaign=user-share\u0026fbclid=IwAR3dXop_cQSa1EJIj23zDgWEQTHOfB4KtHu0VG5ezI4pO7LEth67rA77s7k\"\u003ehttps://denvergazette.com/…/article_a5ef2dee-9577-5222-90ad…\u003c/a\u003e\u003c/p\u003e\u003ca href=\"https://denvergazette.com/news/local/sentence-reduced-for-abused-teen-who-got-life-for-killing-denver-police-officer-in-1995/article_a5ef2dee-9577-5222-90ad-f3eefd8dacc9.html?utm_medium=social\u0026utm_source=facebook\u0026utm_campaign=user-share\"\u003eDenver District Attorney Beth McCann decided “extraordinary mitigating circumstances” warranted the reduction in the sentence — and eventual release from prison — of a man sentenced as a juvenile to\u003cimg src=\"https://external.fapa1-1.fna.fbcdn.net/safe_image.php?d=AQGTeApBqFaUcr9j\u0026w=160\u0026h=160\u0026url=https%3A%2F%2Fbloximages.newyork1.vip.townnews.com%2Fdenvergazette.com%2Fcontent%2Ftncms%2Fassets%2Fv3%2Feditorial%2F4%2F5d%2F45d3bf46-4ff0-5021-b586-3886b20ee444%2F5fe386821e06e.image.jpg%3Fresize%3D320%252C475\u0026cfs=1\u0026upscale=1\u0026fallback=news_d_placeholder_publisher_square\u0026_nc_cb=1\u0026_nc_hash=AQGQjF90gFvcE9nK\" alt=\"\" width=\"158\" height=\"158\" caption=\"\" /\u003e\u003c/a\u003e\u003cp\u003edenvergazette.com\u003c/p\u003e\u003cp\u003eSentence reduced for abused teen who got life for killing Denver police officer in 1995\u003c/p\u003eDenver District Attorney Beth McCann decided “extraordinary mitigating circumstances” warranted the reduction in the sentence — and eventual release from prison — of a man sentenced as a juvenile to\u003ca href=\"https://denvergazette.com/news/local/sentence-reduced-for-abused-teen-who-got-life-for-killing-denver-police-officer-in-1995/article_a5ef2dee-9577-5222-90ad-f3eefd8dacc9.html?utm_medium=social\u0026utm_source=facebook\u0026utm_campaign=user-share\"\u003eDenver District Attorney Beth McCann decided “extraordinary mitigating circumstances” warranted the reduction in the sentence — and eventual release from prison — of a man sentenced as a juvenile to\u003c/a\u003e",
      "date_published": "2020-12-23T20:39:10-07:00",
      "date_modified": "2020-12-23T20:39:10-07:00",
      "author": {
        "name": "Colorado Attorneys Against Police Violence"
      }
    },
    {
      "id": "https://www.facebook.com/197917375303938",
      "url": "https://www.facebook.com/197917375303938",
      "title": "https://www.google.com/…/366c57a8-445e-11eb-975c-d17b8815a6…",
      "content_html": "\u003ca href=\"https://www.facebook.com/Colorado-Attorneys-Against-Police-Violence-106087521153591/\"\u003e\u003cimg src=\"https://scontent.fapa1-1.fna.fbcdn.net/v/t1.0-1/cp0/c23.0.50.50a/p50x50/118569704_145892603839749_1971037107782593743_n.png?_nc_cat=108\u0026ccb=2\u0026_nc_sid=dbb9e7\u0026_nc_ohc=m3os2-uLM0MAX_OEXRa\u0026_nc_ht=scontent.fapa1-1.fna\u0026_nc_tp=30\u0026oh=052ffa638da2b30bbb6033dbbd5bec94\u0026oe=6013C7AF\" alt=\"\" /\u003e\u003c/a\u003e\u003ca href=\"https://www.facebook.com/Colorado-Attorneys-Against-Police-Violence-106087521153591/\"\u003eColorado Attorneys Against Police Violence\u003c/a\u003e\u003ca href=\"https://www.facebook.com/permalink.php\"\u003e\u003c/a\u003e\u003ci\u003e\u003c/i\u003e\u003cp\u003e\u003ca href=\"https://www.google.com/amp/s/www.washingtonpost.com/local/legal-issues/courtroom-portraits-judges-ruling/2020/12/22/366c57a8-445e-11eb-975c-d17b8815a66d_story.html%3foutputType=amp?fbclid=IwAR3hDSY5BCo91YjXpRfjkiJqgQcl0qKEFOC5NKjPKO2ET0D0ayD3LJ8GaR4\"\u003ehttps://www.google.com/…/366c57a8-445e-11eb-975c-d17b8815a6…\u003c/a\u003e\u003c/p\u003e\u003ca href=\"https://www.google.com/amp/s/www.washingtonpost.com/local/legal-issues/courtroom-portraits-judges-ruling/2020/12/22/366c57a8-445e-11eb-975c-d17b8815a66d_story.html%3foutputType=amp\"\u003eDavid Bernhard wrote in an opinion that the portraits create the perception the justice system is biased.\u003cimg src=\"https://external.fapa1-1.fna.fbcdn.net/safe_image.php?d=AQGJ7x8UZZpyMP20\u0026w=540\u0026h=282\u0026url=https%3A%2F%2Fwww.washingtonpost.com%2Fwp-apps%2Fimrs.php%3Fsrc%3Dhttps%3A%2F%2Farc-anglerfish-washpost-prod-washpost.s3.amazonaws.com%2Fpublic%2FOOPUSVQKSUI6HCP6VO2KKBTQCQ.jpg%26w%3D1440\u0026cfs=1\u0026upscale=1\u0026fallback=news_d_placeholder_publisher\u0026_nc_cb=1\u0026_nc_hash=AQH611NKYUxPpuHh\" alt=\"\" width=\"500\" height=\"262\" caption=\"\" /\u003e\u003c/a\u003e\u003cp\u003ewashingtonpost.com\u003c/p\u003e\u003cp\u003eVa. judge rules Black defendant can’t get a fair trial in courtroom largely featuring portraits of White judges\u003c/p\u003eDavid Bernhard wrote in an opinion that the portraits create the perception the justice system is biased.\u003ca href=\"https://www.google.com/amp/s/www.washingtonpost.com/local/legal-issues/courtroom-portraits-judges-ruling/2020/12/22/366c57a8-445e-11eb-975c-d17b8815a66d_story.html%3foutputType=amp\"\u003eDavid Bernhard wrote in an opinion that the portraits create the perception the justice system is biased.\u003c/a\u003e",
      "date_published": "2020-12-22T20:25:32-07:00",
      "date_modified": "2020-12-22T20:25:32-07:00",
      "author": {
        "name": "Colorado Attorneys Against Police Violence"
      }
    },
    {
      "id": "https://www.facebook.com/197554568673552",
      "url": "https://www.facebook.com/197554568673552",
      "title": "today! 4p! come tell gov. polis to treat jails and prisons like...",
      "content_html": "\u003ca href=\"https://www.facebook.com/Colorado-Attorneys-Against-Police-Violence-106087521153591/\"\u003e\u003cimg src=\"https://scontent.fapa1-1.fna.fbcdn.net/v/t1.0-1/cp0/c23.0.50.50a/p50x50/118569704_145892603839749_1971037107782593743_n.png?_nc_cat=108\u0026ccb=2\u0026_nc_sid=dbb9e7\u0026_nc_ohc=m3os2-uLM0MAX_OEXRa\u0026_nc_ht=scontent.fapa1-1.fna\u0026_nc_tp=30\u0026oh=052ffa638da2b30bbb6033dbbd5bec94\u0026oe=6013C7AF\" alt=\"\" /\u003e\u003c/a\u003e\u003ca href=\"https://www.facebook.com/Colorado-Attorneys-Against-Police-Violence-106087521153591/\"\u003eColorado Attorneys Against Police Violence\u003c/a\u003e\u003ca href=\"https://www.facebook.com/permalink.php\"\u003e\u003c/a\u003e\u003ci\u003e\u003c/i\u003e\u003cp\u003etoday! 4p! come tell gov. polis to treat jails and prisons like the public health crises they are, and to bring our incarcerated neighbors home. \u003ca href=\"https://www.facebook.com/hashtag/caapv\"\u003e#CAAPV\u003c/a\u003e\u003c/p\u003e\u003ca href=\"https://www.facebook.com/106087521153591/photos/pcb.197554568673552/197554522006890/\"\u003e\u003cimg src=\"https://scontent.fapa1-2.fna.fbcdn.net/v/t1.0-0/s261x260/131662619_197554528673556_2577237318484292429_n.jpg?_nc_cat=104\u0026ccb=2\u0026_nc_sid=9e2e56\u0026_nc_ohc=Oc7DeK-jyZgAX_yTlR-\u0026_nc_ht=scontent.fapa1-2.fna\u0026tp=7\u0026oh=c2c2d6fbfdb8a56acccf769245cee28c\u0026oe=6014EE4D\" alt=\"Image may contain: text that says 'COVID-19 IN CO PRISONS: GOV. POLIS' NIGHTMARE BEFORE CHRISTMAS 1 in 8 Incarcerated People in CO have COVID-19 Governor Polis can stop this crisis. Co Attorneys Against Police Violence Festive Honk \u0026 Wave Action 4:00p, December 22, 2020 Governor's Mansion'\" width=\"250\" height=\"250\" caption=\"Image may contain: text that says 'COVID-19 IN CO PRISONS: GOV. POLIS' NIGHTMARE BEFORE CHRISTMAS 1 in 8 Incarcerated People in CO have COVID-19 Governor Polis can stop this crisis. Co Attorneys Against Police Violence Festive Honk \u0026 Wave Action 4:00p, December 22, 2020 Governor's Mansion'\" /\u003e\u003c/a\u003e\u003ca href=\"https://www.facebook.com/106087521153591/photos/pcb.197554568673552/197554525340223/\"\u003e\u003cimg src=\"https://scontent.fapa1-2.fna.fbcdn.net/v/t1.0-0/p261x260/132260423_197554532006889_7600664924704331439_o.jpg?_nc_cat=109\u0026ccb=2\u0026_nc_sid=9e2e56\u0026_nc_ohc=KbKMANQMQLsAX8jZKdw\u0026_nc_ht=scontent.fapa1-2.fna\u0026tp=6\u0026oh=d85c53af916d976d5a10538b7987e5e4\u0026oe=601431AC\" alt=\"Image may contain: text that says 'PRISONS \u0026 JAILS ARE A PUBLIC HEALTH CRISIS DECEMBER 2020 COVID-19IS RAVAGING JAILS AND PRISONS largest PRIORITY VACCINATION DECARCERATION ee execution among NO COLORADO EXCEPTION Mass jails CAAPV'\" width=\"250\" height=\"250\" caption=\"Image may contain: text that says 'PRISONS \u0026 JAILS ARE A PUBLIC HEALTH CRISIS DECEMBER 2020 COVID-19IS RAVAGING JAILS AND PRISONS largest PRIORITY VACCINATION DECARCERATION ee execution among NO COLORADO EXCEPTION Mass jails CAAPV'\" /\u003e\u003c/a\u003e",
      "date_published": "2020-12-22T07:19:05-07:00",
      "date_modified": "2020-12-22T07:19:05-07:00",
      "author": {
        "name": "Colorado Attorneys Against Police Violence"
      }
    },
    {
      "id": "https://www.facebook.com/106087521153591/photos/a.107461271016216/197124982049844/",
      "url": "https://www.facebook.com/106087521153591/photos/a.107461271016216/197124982049844/",
      "title": "Like the Ghosts of Christmas past, present, and future, CAAPV is...",
      "content_html": "\u003ca href=\"https://www.facebook.com/Colorado-Attorneys-Against-Police-Violence-106087521153591/\"\u003e\u003cimg src=\"https://scontent.fapa1-1.fna.fbcdn.net/v/t1.0-1/cp0/c23.0.50.50a/p50x50/118569704_145892603839749_1971037107782593743_n.png?_nc_cat=108\u0026ccb=2\u0026_nc_sid=dbb9e7\u0026_nc_ohc=m3os2-uLM0MAX_OEXRa\u0026_nc_ht=scontent.fapa1-1.fna\u0026_nc_tp=30\u0026oh=052ffa638da2b30bbb6033dbbd5bec94\u0026oe=6013C7AF\" alt=\"\" /\u003e\u003c/a\u003e\u003ca href=\"https://www.facebook.com/Colorado-Attorneys-Against-Police-Violence-106087521153591/\"\u003eColorado Attorneys Against Police Violence\u003c/a\u003e\u003ca href=\"https://www.facebook.com/106087521153591/photos/a.107461271016216/197124982049844/\"\u003e\u003c/a\u003e\u003ci\u003e\u003c/i\u003e\u003cp\u003eLike the Ghosts of Christmas past, present, and future, CAAPV is going to visit the Governor tomorrow and ask that he bring our neighbors home. While he may have ended the death penalty, COVID-19 in prison is still a death sentence. \u003c/p\u003e\u003cp\u003e Please spread the word and join us in any way you can! \u003c/p\u003e\u003cp\u003e \u003ca href=\"https://www.facebook.com/hashtag/caapv\"\u003e#CAAPV\u003c/a\u003e\u003c/p\u003e\u003ca href=\"https://www.facebook.com/106087521153591/photos/a.107461271016216/197124982049844/\"\u003e\u003cimg src=\"https://scontent.fapa1-1.fna.fbcdn.net/v/t1.0-0/p526x296/132148533_197124985383177_8272549345054126213_n.jpg?_nc_cat=108\u0026ccb=2\u0026_nc_sid=110474\u0026_nc_ohc=y49EHfjObrwAX_WyCom\u0026_nc_ht=scontent.fapa1-1.fna\u0026tp=6\u0026oh=abb794077e7924866517d330b75eadff\u0026oe=60153C3E\" alt=\"Image may contain: text that says 'COVID-19 IN CO PRISONS: GOV. POLIS' NIGHTMARE BEFORE CHRISTMAS 1 in 8 Incarcerated People in CO have COVID-19 Governor Polis can stop this crisis. Co Attorneys Against Police Violence Festive Honk \u0026 Wave Action 4:00p, December 22, 2020 Governor's Mansion'\" width=\"500\" height=\"500\" caption=\"Image may contain: text that says 'COVID-19 IN CO PRISONS: GOV. POLIS' NIGHTMARE BEFORE CHRISTMAS 1 in 8 Incarcerated People in CO have COVID-19 Governor Polis can stop this crisis. Co Attorneys Against Police Violence Festive Honk \u0026 Wave Action 4:00p, December 22, 2020 Governor's Mansion'\" /\u003e\u003c/a\u003e",
      "date_published": "2020-12-21T16:54:20-07:00",
      "date_modified": "2020-12-21T16:54:20-07:00",
      "author": {
        "name": "Colorado Attorneys Against Police Violence"
      }
    },
    {
      "id": "https://www.facebook.com/196926198736389",
      "url": "https://www.facebook.com/196926198736389",
      "title": "...",
      "content_html": "\u003ca href=\"https://www.facebook.com/Colorado-Attorneys-Against-Police-Violence-106087521153591/\"\u003e\u003cimg src=\"https://scontent.fapa1-1.fna.fbcdn.net/v/t1.0-1/cp0/c23.0.50.50a/p50x50/118569704_145892603839749_1971037107782593743_n.png?_nc_cat=108\u0026ccb=2\u0026_nc_sid=dbb9e7\u0026_nc_ohc=m3os2-uLM0MAX_OEXRa\u0026_nc_ht=scontent.fapa1-1.fna\u0026_nc_tp=30\u0026oh=052ffa638da2b30bbb6033dbbd5bec94\u0026oe=6013C7AF\" alt=\"\" /\u003e\u003c/a\u003e\u003ca href=\"https://www.facebook.com/Colorado-Attorneys-Against-Police-Violence-106087521153591/\"\u003eColorado Attorneys Against Police Violence\u003c/a\u003e\u003ca href=\"https://www.facebook.com/permalink.php\"\u003e\u003c/a\u003e\u003ci\u003e\u003c/i\u003e\u003cp\u003e\u003ca href=\"https://www.chieftain.com/story/news/2020/12/17/colorado-prison-inmates-fear-covid-19-could-death-sentence/3927606001/?fbclid=IwAR2sy8kMYeTjz7z8-8o82HoUL9nX5RvziW6GsdS3iJ8gq-jXJBbfgrMGvDM\"\u003ehttps://www.chieftain.com/…/colorado-prison-in…/3927606001/…\u003c/a\u003e\u003c/p\u003e\u003ca href=\"https://www.chieftain.com/story/news/2020/12/17/colorado-prison-inmates-fear-covid-19-could-death-sentence/3927606001/\"\u003eSome older inmates are hoping to get out of prison for fear the coronavirus could be a death sentence.\u003cimg src=\"https://external.fapa1-1.fna.fbcdn.net/safe_image.php?d=AQEmSEWnPtOmVdbI\u0026w=540\u0026h=282\u0026url=https%3A%2F%2Fwww.gannett-cdn.com%2Fpresto%2F2020%2F12%2F16%2FNTPC%2F49c070e7-582c-40eb-b1cb-625f7002fe0a-EastCanonPrisonComplexwithFlags.jpg%3Fcrop%3D1799%2C1012%2Cx0%2Cy91%26width%3D1799%26height%3D1012%26format%3Dpjpg%26auto%3Dwebp\u0026cfs=1\u0026upscale=1\u0026fallback=news_d_placeholder_publisher\u0026_nc_cb=1\u0026_nc_hash=AQE_uA-xJ-OQ_smE\" alt=\"\" width=\"500\" height=\"262\" caption=\"\" /\u003e\u003c/a\u003e\u003cp\u003echieftain.com\u003c/p\u003e\u003cp\u003eIs COVID-19 a death sentence for some Colorado inmates?\u003c/p\u003eSome older inmates are hoping to get out of prison for fear the coronavirus could be a death sentence.\u003ca href=\"https://www.chieftain.com/story/news/2020/12/17/colorado-prison-inmates-fear-covid-19-could-death-sentence/3927606001/\"\u003eSome older inmates are hoping to get out of prison for fear the coronavirus could be a death sentence.\u003c/a\u003e",
      "date_published": "2020-12-21T09:14:24-07:00",
      "date_modified": "2020-12-21T09:14:24-07:00",
      "author": {
        "name": "Colorado Attorneys Against Police Violence"
      }
    },
    {
      "id": "https://www.facebook.com/196513882110954",
      "url": "https://www.facebook.com/196513882110954",
      "title": "https://www.themarshallproject.org/…/colorado-tries-new-way…",
      "content_html": "\u003ca href=\"https://www.facebook.com/Colorado-Attorneys-Against-Police-Violence-106087521153591/\"\u003e\u003cimg src=\"https://scontent.fapa1-1.fna.fbcdn.net/v/t1.0-1/cp0/c23.0.50.50a/p50x50/118569704_145892603839749_1971037107782593743_n.png?_nc_cat=108\u0026ccb=2\u0026_nc_sid=dbb9e7\u0026_nc_ohc=m3os2-uLM0MAX_OEXRa\u0026_nc_ht=scontent.fapa1-1.fna\u0026_nc_tp=30\u0026oh=052ffa638da2b30bbb6033dbbd5bec94\u0026oe=6013C7AF\" alt=\"\" /\u003e\u003c/a\u003e\u003ca href=\"https://www.facebook.com/Colorado-Attorneys-Against-Police-Violence-106087521153591/\"\u003eColorado Attorneys Against Police Violence\u003c/a\u003e\u003ca href=\"https://www.facebook.com/permalink.php\"\u003e\u003c/a\u003e\u003ci\u003e\u003c/i\u003e\u003cp\u003e\u003ca href=\"https://www.themarshallproject.org/2020/12/18/colorado-tries-new-way-to-punish-rogue-cops?utm_medium=social\u0026utm_campaign=share-tools\u0026utm_source=facebook\u0026utm_content=post-top\u0026fbclid=IwAR1f5dic7332jwnxK-BgLPQ-PlErJH1YSRyI6n7KkFOI3yI3pjjkTMWAbnE\"\u003ehttps://www.themarshallproject.org/…/colorado-tries-new-way…\u003c/a\u003e\u003c/p\u003e\u003ca href=\"https://www.themarshallproject.org/2020/12/18/colorado-tries-new-way-to-punish-rogue-cops?utm_medium=social\u0026utm_campaign=share-tools\u0026utm_source=facebook\u0026utm_content=post-top\"\u003eIndividual officers can’t claim ‘qualified immunity’ in excessive force cases, but may not end up paying damages out of their own pockets.\u003cimg src=\"https://external.fapa1-1.fna.fbcdn.net/safe_image.php?d=AQHqmTWHjva3LADZ\u0026w=540\u0026h=282\u0026url=https%3A%2F%2Fd1n0c1ufntxbvh.cloudfront.net%2Fphoto%2Faa3bbde8%2F63199%2F1200x%2F\u0026cfs=1\u0026upscale=1\u0026fallback=news_d_placeholder_publisher\u0026_nc_cb=1\u0026_nc_hash=AQEj4Byf0Cch6wuR\" alt=\"\" width=\"500\" height=\"262\" caption=\"\" /\u003e\u003c/a\u003e\u003cp\u003ethemarshallproject.org\u003c/p\u003e\u003cp\u003eColorado Tries New Way To Punish Rogue Cops\u003c/p\u003eIndividual officers can’t claim ‘qualified immunity’ in excessive force cases, but may not end up paying damages out of their own pockets.\u003ca href=\"https://www.themarshallproject.org/2020/12/18/colorado-tries-new-way-to-punish-rogue-cops?utm_medium=social\u0026utm_campaign=share-tools\u0026utm_source=facebook\u0026utm_content=post-top\"\u003eIndividual officers can’t claim ‘qualified immunity’ in excessive force cases, but may not end up paying damages out of their own pockets.\u003c/a\u003e",
      "date_published": "2020-12-20T17:54:14-07:00",
      "date_modified": "2020-12-20T17:54:14-07:00",
      "author": {
        "name": "Colorado Attorneys Against Police Violence"
      }
    },
    {
      "id": "https://www.facebook.com/196466032115739",
      "url": "https://www.facebook.com/196466032115739",
      "title": "allowing the state to murder lisa says far more about us than it...",
      "content_html": "\u003ca href=\"https://www.facebook.com/Colorado-Attorneys-Against-Police-Violence-106087521153591/\"\u003e\u003cimg src=\"https://scontent.fapa1-1.fna.fbcdn.net/v/t1.0-1/cp0/c23.0.50.50a/p50x50/118569704_145892603839749_1971037107782593743_n.png?_nc_cat=108\u0026ccb=2\u0026_nc_sid=dbb9e7\u0026_nc_ohc=m3os2-uLM0MAX_OEXRa\u0026_nc_ht=scontent.fapa1-1.fna\u0026_nc_tp=30\u0026oh=052ffa638da2b30bbb6033dbbd5bec94\u0026oe=6013C7AF\" alt=\"\" /\u003e\u003c/a\u003e\u003ca href=\"https://www.facebook.com/Colorado-Attorneys-Against-Police-Violence-106087521153591/\"\u003eColorado Attorneys Against Police Violence\u003c/a\u003e\u003ca href=\"https://www.facebook.com/permalink.php\"\u003e\u003c/a\u003e\u003ci\u003e\u003c/i\u003e\u003cp\u003eallowing the state to murder lisa says far more about us than it does about her. \u003ca href=\"https://www.facebook.com/hashtag/abolishdeath\"\u003e#AbolishDeath\u003c/a\u003e\u003c/p\u003e\u003cp\u003e \u003ca href=\"https://www.nytimes.com/2020/12/18/opinion/sunday/lisa-montgomery-execution.html?fbclid=IwAR01rwm1-JUXtLwIyiYxQSCbBK9AAXEm-s_8DSxzlsnAnkAejMdAhiXiHbE\"\u003ehttps://www.nytimes.com/…/s…/lisa-montgomery-execution.html…\u003c/a\u003e\u003c/p\u003e\u003ca href=\"https://www.nytimes.com/2020/12/18/opinion/sunday/lisa-montgomery-execution.html\"\u003eThe execution of Lisa Montgomery would be an injustice on top of an injustice.\u003cimg src=\"https://external.fapa1-1.fna.fbcdn.net/safe_image.php?d=AQEAMiDeUFmyzDpg\u0026w=540\u0026h=282\u0026url=https%3A%2F%2Fstatic01.nyt.com%2Fimages%2F2020%2F12%2F20%2Fopinion%2Fsunday%2F20synder%2F20synder-facebookJumbo-v2.jpg\u0026cfs=1\u0026upscale=1\u0026fallback=news_d_placeholder_publisher\u0026_nc_cb=1\u0026_nc_hash=AQGbNFeAJgp5nntn\" alt=\"\" width=\"500\" height=\"262\" caption=\"\" /\u003e\u003c/a\u003e\u003cp\u003enytimes.com\u003c/p\u003e\u003cp\u003eOpinion | Punch After Punch, Rape After Rape, a Murderer Was Made\u003c/p\u003eThe execution of Lisa Montgomery would be an injustice on top of an injustice.\u003ca href=\"https://www.nytimes.com/2020/12/18/opinion/sunday/lisa-montgomery-execution.html\"\u003eThe execution of Lisa Montgomery would be an injustice on top of an injustice.\u003c/a\u003e",
      "date_published": "2020-12-20T15:42:03-07:00",
      "date_modified": "2020-12-20T15:42:03-07:00",
      "author": {
        "name": "Colorado Attorneys Against Police Violence"
      }
    },
    {
      "id": "https://www.facebook.com/195656592196683",
      "url": "https://www.facebook.com/195656592196683",
      "title": "prisons. are. a. public. health. crisis. ...",
      "content_html": "\u003ca href=\"https://www.facebook.com/Colorado-Attorneys-Against-Police-Violence-106087521153591/\"\u003e\u003cimg src=\"https://scontent.fapa1-1.fna.fbcdn.net/v/t1.0-1/cp0/c23.0.50.50a/p50x50/118569704_145892603839749_1971037107782593743_n.png?_nc_cat=108\u0026ccb=2\u0026_nc_sid=dbb9e7\u0026_nc_ohc=m3os2-uLM0MAX_OEXRa\u0026_nc_ht=scontent.fapa1-1.fna\u0026_nc_tp=30\u0026oh=052ffa638da2b30bbb6033dbbd5bec94\u0026oe=6013C7AF\" alt=\"\" /\u003e\u003c/a\u003e\u003ca href=\"https://www.facebook.com/Colorado-Attorneys-Against-Police-Violence-106087521153591/\"\u003eColorado Attorneys Against Police Violence\u003c/a\u003e\u003ca href=\"https://www.facebook.com/permalink.php\"\u003e\u003c/a\u003e\u003ci\u003e\u003c/i\u003e\u003cp\u003eprisons. are. a. public. health. crisis. \u003c/p\u003e\u003cp\u003e \u003ca href=\"https://www.denverpost.com/2020/12/19/colorado-prisons-coronavirus-staffing-conditions/?fbclid=IwAR1vNV2XaaUgcOUYw6aipUzz8_PwaUFOFmpyTZi0wiqouAcgnoOUH2mMPJQ\"\u003ehttps://www.denverpost.com/…/colorado-prisons-coronavirus…/…\u003c/a\u003e\u003c/p\u003e\u003ca href=\"https://www.denverpost.com/2020/12/19/colorado-prisons-coronavirus-staffing-conditions/\"\u003ePrisoners are being fed substandard meals — sometimes as little as two slices of bread, a piece of bologna, and an apple — and sometimes are not able to access showers for days at a tim…\u003cimg src=\"https://external.fapa1-1.fna.fbcdn.net/safe_image.php?d=AQEucc-dpRZOwCce\u0026w=540\u0026h=282\u0026url=https%3A%2F%2Fwww.denverpost.com%2Fwp-content%2Fuploads%2F2020%2F12%2FTDP-L-PORTRAITS-RE-_FJA8519.jpg%3Fw%3D1024%26h%3D725\u0026cfs=1\u0026upscale=1\u0026fallback=news_d_placeholder_publisher\u0026_nc_cb=1\u0026_nc_hash=AQFYsKJwznvJJlwZ\" alt=\"\" width=\"500\" height=\"262\" caption=\"\" /\u003e\u003c/a\u003e\u003cp\u003edenverpost.com\u003c/p\u003e\u003cp\u003eStaff shortages, extended lockdowns in coronavirus-ridden Colorado prisons create “tenuous” situations\u003c/p\u003ePrisoners are being fed substandard meals — sometimes as little as two slices of bread, a piece of bologna, and an apple — and sometimes are not able to access showers for days at a tim…\u003ca href=\"https://www.denverpost.com/2020/12/19/colorado-prisons-coronavirus-staffing-conditions/\"\u003ePrisoners are being fed substandard meals — sometimes as little as two slices of bread, a piece of bologna, and an apple — and sometimes are not able to access showers for days at a tim…\u003c/a\u003e",
      "date_published": "2020-12-19T08:57:30-07:00",
      "date_modified": "2020-12-19T08:57:30-07:00",
      "author": {
        "name": "Colorado Attorneys Against Police Violence"
      }
    },
    {
      "id": "https://www.facebook.com/195000518928957",
      "url": "https://www.facebook.com/195000518928957",
      "title": "#DYK: prisons and jails are a public health crisis.  #CAAPV...",
      "content_html": "\u003ca href=\"https://www.facebook.com/Colorado-Attorneys-Against-Police-Violence-106087521153591/\"\u003e\u003cimg src=\"https://scontent.fapa1-1.fna.fbcdn.net/v/t1.0-1/cp0/c23.0.50.50a/p50x50/118569704_145892603839749_1971037107782593743_n.png?_nc_cat=108\u0026ccb=2\u0026_nc_sid=dbb9e7\u0026_nc_ohc=m3os2-uLM0MAX_OEXRa\u0026_nc_ht=scontent.fapa1-1.fna\u0026_nc_tp=30\u0026oh=052ffa638da2b30bbb6033dbbd5bec94\u0026oe=6013C7AF\" alt=\"\" /\u003e\u003c/a\u003e\u003ca href=\"https://www.facebook.com/Colorado-Attorneys-Against-Police-Violence-106087521153591/\"\u003eColorado Attorneys Against Police Violence\u003c/a\u003e\u003ca href=\"https://www.facebook.com/permalink.php\"\u003e\u003c/a\u003e\u003ci\u003e\u003c/i\u003e\u003cp\u003e\u003ca href=\"https://www.facebook.com/hashtag/dyk\"\u003e#DYK\u003c/a\u003e: prisons and jails are a public health crisis. \u003c/p\u003e\u003cp\u003e \u003ca href=\"https://www.facebook.com/hashtag/caapv\"\u003e#CAAPV\u003c/a\u003e urges you to act: tell gov. polis to treat \"incarcerated people\" with respect and dignity and to bring our neighbors home by joining \u003ca href=\"https://www.facebook.com/acluofcolorado/\"\u003eACLU of Colorado\u003c/a\u003e's effort here: \u003ca href=\"https://action.aclu.org/send-message/co-covid-prisons?initms_aff=co\u0026initms_chan=soc\u0026utm_medium=soc\u0026initms=201215_affcampaign_covid-prisons_ats_fb\u0026utm_source=fb\u0026utm_campaign=affcampaign\u0026utm_content=201215_prisonersrights_covid-prisons_ats\u0026ms_aff=co\u0026ms_chan=soc\u0026ms=201215_affcampaign_covid-prisons_ats_fb\u0026fbclid=IwAR2w6b2b6KK1gm9s4VsKd3xnWOpU-0_GCprkmkgj07r99m14FJYUBqqdUiY\"\u003ehttps://action.aclu.org/send-message/co-covid-prisons…\u003c/a\u003e\u003c/p\u003e\u003ca href=\"https://www.facebook.com/106087521153591/photos/pcb.195000518928957/194997632262579/\"\u003e\u003cimg src=\"https://scontent.fapa1-2.fna.fbcdn.net/v/t1.0-0/p296x100/132001711_194997635595912_7403954134455102370_o.jpg?_nc_cat=105\u0026ccb=2\u0026_nc_sid=8024bb\u0026_nc_ohc=jDMzFmkyQnAAX9H4wjB\u0026_nc_ht=scontent.fapa1-2.fna\u0026tp=6\u0026oh=3fa78e4c9cb06a38702b613defee8635\u0026oe=6015428A\" alt=\"Image may contain: text\" width=\"282\" height=\"500\" caption=\"Image may contain: text\" /\u003e\u003c/a\u003e\u003ca href=\"https://www.facebook.com/106087521153591/photos/pcb.195000518928957/194997668929242/\"\u003e\u003cimg src=\"https://scontent.fapa1-1.fna.fbcdn.net/v/t1.0-0/p261x260/131959278_194997675595908_8560272878882856782_o.jpg?_nc_cat=111\u0026ccb=2\u0026_nc_sid=8024bb\u0026_nc_ohc=6XuPhrq_pssAX-XNSFL\u0026_nc_ht=scontent.fapa1-1.fna\u0026tp=6\u0026oh=dcb1e1978a637752a4e0250809560f8d\u0026oe=60156F8B\" alt=\"Image may contain: text that says 'DID YOU KNOW: IN COLORADO THERE ARE CURRENTLY ACTIVE COVID OUTBREAKS in 18 prisons 16 transitional facilities 11 jaiils 12 police/ sheriff departments juvenile prisons 1 immigration prison h CAAPV FB: Colorado Attorneys Against Police Violence ContactCAAPV\u0026#064;gmail. .com'\" width=\"249\" height=\"443\" caption=\"Image may contain: text that says 'DID YOU KNOW: IN COLORADO THERE ARE CURRENTLY ACTIVE COVID OUTBREAKS in 18 prisons 16 transitional facilities 11 jaiils 12 police/ sheriff departments juvenile prisons 1 immigration prison h CAAPV FB: Colorado Attorneys Against Police Violence ContactCAAPV\u0026#064;gmail. .com'\" /\u003e\u003c/a\u003e\u003ca href=\"https://www.facebook.com/106087521153591/photos/pcb.195000518928957/194997665595909/\"\u003e\u003cimg src=\"https://scontent.fapa1-2.fna.fbcdn.net/v/t1.0-0/p261x260/131974979_194997672262575_4635151787768294017_o.jpg?_nc_cat=105\u0026ccb=2\u0026_nc_sid=8024bb\u0026_nc_ohc=3uNhWksp0qoAX-nUfcb\u0026_nc_ht=scontent.fapa1-2.fna\u0026tp=6\u0026oh=c7b9af6825fb954a8231054eb5770beb\u0026oe=601760B0\" alt=\"Image may contain: text that says 'DID YOU KNOW: A recent study has concluded that MASS INCARCERATION led to 560,000 additional COVID-19 cases nationwide in just three months- not just in jails and and prisons, but in the areas that surround them h CAAPV FB: Colorado Attorneys Against AgainstPoliceViolence Police ContactCAAPV\u0026#064;gmail .com'\" width=\"249\" height=\"443\" caption=\"Image may contain: text that says 'DID YOU KNOW: A recent study has concluded that MASS INCARCERATION led to 560,000 additional COVID-19 cases nationwide in just three months- not just in jails and and prisons, but in the areas that surround them h CAAPV FB: Colorado Attorneys Against AgainstPoliceViolence Police ContactCAAPV\u0026#064;gmail .com'\" /\u003e\u003c/a\u003e",
      "date_published": "2020-12-18T08:56:25-07:00",
      "date_modified": "2020-12-18T08:56:25-07:00",
      "author": {
        "name": "Colorado Attorneys Against Police Violence"
      }
    },
    {
      "id": "https://www.facebook.com/194494665646209",
      "url": "https://www.facebook.com/194494665646209",
      "title": "\"Every prisoner executed in 2020 either had a significant...",
      "content_html": "\u003ca href=\"https://www.facebook.com/Colorado-Attorneys-Against-Police-Violence-106087521153591/\"\u003e\u003cimg src=\"https://scontent.fapa1-1.fna.fbcdn.net/v/t1.0-1/cp0/c23.0.50.50a/p50x50/118569704_145892603839749_1971037107782593743_n.png?_nc_cat=108\u0026ccb=2\u0026_nc_sid=dbb9e7\u0026_nc_ohc=m3os2-uLM0MAX_OEXRa\u0026_nc_ht=scontent.fapa1-1.fna\u0026_nc_tp=30\u0026oh=052ffa638da2b30bbb6033dbbd5bec94\u0026oe=6013C7AF\" alt=\"\" /\u003e\u003c/a\u003e\u003ca href=\"https://www.facebook.com/Colorado-Attorneys-Against-Police-Violence-106087521153591/\"\u003eColorado Attorneys Against Police Violence\u003c/a\u003e\u003ca href=\"https://www.facebook.com/permalink.php\"\u003e\u003c/a\u003e\u003ci\u003e\u003c/i\u003e\u003cp\u003e\"Every prisoner executed in 2020 either had a significant mental impairment (serious mental illness, brain damage or IQ in the intellectually disabled range, or chronic trauma) or was a teenager at the time of the crime. The year’s executions also highlighted numerous systemic problems in the application of the death penalty, including racial bias, the violation of Native American tribal sovereignty, disregarding the wishes of victims’ family members, ineffective representation, and inadequate appellate review.\"\u003c/p\u003e\u003cp\u003e \u003ca href=\"https://deathpenaltyinfo.org/news/dpic-2020-year-end-report-death-penalty-hits-historic-lows-despite-federal-execution-spree\"\u003ehttps://deathpenaltyinfo.org/…/dpic-2020-year-end-report-de…\u003c/a\u003e\u003c/p\u003e\u003ca href=\"https://deathpenaltyinfo.org/news/dpic-2020-year-end-report-death-penalty-hits-historic-lows-despite-federal-execution-spree\"\u003eDeath sentences reached their lowest level in the modern era and executions hit a generational low despite an historically anomalous federal execution spree, according to the 2020 Year End Report from the Death Penalty Information Center. At the same time, ignoring public health warnings and…\u003cimg src=\"https://external.fapa1-1.fna.fbcdn.net/safe_image.php?d=AQG_y23LkY--tVHT\u0026w=540\u0026h=282\u0026url=https%3A%2F%2Fdpic.imgix.net%2FDPIC-2020-YER-Dashboard.png%3Fauto%3Dformat%26crop%3Dfocalpoint%26domain%3Ddpic.imgix.net%26fit%3Dcrop%26fp-x%3D0.5%26fp-y%3D0.5%26h%3D630%26ixlib%3Dphp-3.3.0%26q%3D82%26w%3D1200%26s%3D2bbdbc71b3caa1031f86cf2b3dfc4904\u0026cfs=1\u0026upscale=1\u0026fallback=news_d_placeholder_publisher\u0026_nc_cb=1\u0026_nc_hash=AQFjWTKsid-qIcIt\" alt=\"\" width=\"500\" height=\"262\" caption=\"\" /\u003e\u003c/a\u003e\u003cp\u003edeathpenaltyinfo.org\u003c/p\u003e\u003cp\u003eDPIC 2020 Year End Report: Death Penalty Hits Historic Lows Despite Federal Execution Spree\u003c/p\u003eDeath sentences reached their lowest level in the modern era and executions hit a generational low despite an historically anomalous federal execution spree, according to the 2020 Year End Report from the Death Penalty Information Center. At the same time, ignoring public health warnings and…\u003ca href=\"https://deathpenaltyinfo.org/news/dpic-2020-year-end-report-death-penalty-hits-historic-lows-despite-federal-execution-spree\"\u003eDeath sentences reached their lowest level in the modern era and executions hit a generational low despite an historically anomalous federal execution spree, according to the 2020 Year End Report from the Death Penalty Information Center. At the same time, ignoring public health warnings and…\u003c/a\u003e",
      "date_published": "2020-12-17T15:41:06-07:00",
      "date_modified": "2020-12-17T15:41:06-07:00",
      "author": {
        "name": "Colorado Attorneys Against Police Violence"
      }
    },
    {
      "id": "https://www.facebook.com/194450335650642",
      "url": "https://www.facebook.com/194450335650642",
      "title": "...",
      "content_html": "\u003ca href=\"https://www.facebook.com/Colorado-Attorneys-Against-Police-Violence-106087521153591/\"\u003e\u003cimg src=\"https://scontent.fapa1-1.fna.fbcdn.net/v/t1.0-1/cp0/c23.0.50.50a/p50x50/118569704_145892603839749_1971037107782593743_n.png?_nc_cat=108\u0026ccb=2\u0026_nc_sid=dbb9e7\u0026_nc_ohc=m3os2-uLM0MAX_OEXRa\u0026_nc_ht=scontent.fapa1-1.fna\u0026_nc_tp=30\u0026oh=052ffa638da2b30bbb6033dbbd5bec94\u0026oe=6013C7AF\" alt=\"\" /\u003e\u003c/a\u003e\u003ca href=\"https://www.facebook.com/Colorado-Attorneys-Against-Police-Violence-106087521153591/\"\u003eColorado Attorneys Against Police Violence\u003c/a\u003e\u003ca href=\"https://www.facebook.com/permalink.php\"\u003e\u003c/a\u003e\u003ci\u003e\u003c/i\u003e\u003cp\u003e\u003ca href=\"https://www.5280.com/2020/12/how-2020-has-affected-the-way-we-hold-law-enforcement-accountable/?fbclid=IwAR3wknjjKeuLzDWsMyF5oDXldOcckNgxBx3aOwOTLGU0F5DmijBUEKyYktA\"\u003ehttps://www.5280.com/…/how-2020-has-affected-the-way-we-h…/…\u003c/a\u003e\u003c/p\u003e\u003ca href=\"https://www.5280.com/2020/12/how-2020-has-affected-the-way-we-hold-law-enforcement-accountable/\"\u003eIn June, Colorado passed SB217, one of the most thorough police accountability bills in the country. How it impacts the state remains to be seen.\u003cimg src=\"https://external.fapa1-1.fna.fbcdn.net/safe_image.php?d=AQEc3BXJ_RDG0_7x\u0026w=540\u0026h=282\u0026url=https%3A%2F%2Fcdn.5280.com%2F2020%2F12%2Faurora-police_robert-sanchez.jpg\u0026cfs=1\u0026upscale=1\u0026fallback=news_d_placeholder_publisher\u0026_nc_cb=1\u0026_nc_hash=AQEi1JcFN2G0foFv\" alt=\"\" width=\"500\" height=\"262\" caption=\"\" /\u003e\u003c/a\u003e\u003cp\u003e5280.com\u003c/p\u003e\u003cp\u003eColorado's Police Accountability Bill Is Historic. But Is It Enough?\u003c/p\u003eIn June, Colorado passed SB217, one of the most thorough police accountability bills in the country. How it impacts the state remains to be seen.\u003ca href=\"https://www.5280.com/2020/12/how-2020-has-affected-the-way-we-hold-law-enforcement-accountable/\"\u003eIn June, Colorado passed SB217, one of the most thorough police accountability bills in the country. How it impacts the state remains to be seen.\u003c/a\u003e",
      "date_published": "2020-12-17T13:55:49-07:00",
      "date_modified": "2020-12-17T13:55:49-07:00",
      "author": {
        "name": "Colorado Attorneys Against Police Violence"
      }
    },
    {
      "id": "https://www.facebook.com/194433915652284",
      "url": "https://www.facebook.com/194433915652284",
      "title": "https://www.cpr.org/…/of-course-it-feels-unsafe-colorado-p…/",
      "content_html": "\u003ca href=\"https://www.facebook.com/Colorado-Attorneys-Against-Police-Violence-106087521153591/\"\u003e\u003cimg src=\"https://scontent.fapa1-1.fna.fbcdn.net/v/t1.0-1/cp0/c23.0.50.50a/p50x50/118569704_145892603839749_1971037107782593743_n.png?_nc_cat=108\u0026ccb=2\u0026_nc_sid=dbb9e7\u0026_nc_ohc=m3os2-uLM0MAX_OEXRa\u0026_nc_ht=scontent.fapa1-1.fna\u0026_nc_tp=30\u0026oh=052ffa638da2b30bbb6033dbbd5bec94\u0026oe=6013C7AF\" alt=\"\" /\u003e\u003c/a\u003e\u003ca href=\"https://www.facebook.com/Colorado-Attorneys-Against-Police-Violence-106087521153591/\"\u003eColorado Attorneys Against Police Violence\u003c/a\u003e\u003ca href=\"https://www.facebook.com/permalink.php\"\u003e\u003c/a\u003e\u003ci\u003e\u003c/i\u003e\u003cp\u003e\u003ca href=\"https://www.cpr.org/2020/12/17/of-course-it-feels-unsafe-colorado-prisons-face-staffing-crisis-as-hundreds-of-guards-inmates-sickened/\"\u003ehttps://www.cpr.org/…/of-course-it-feels-unsafe-colorado-p…/\u003c/a\u003e\u003c/p\u003e\u003ca href=\"https://www.cpr.org/2020/12/17/of-course-it-feels-unsafe-colorado-prisons-face-staffing-crisis-as-hundreds-of-guards-inmates-sickened/\"\u003eParole officers, correctional officers and advocates and families of inmates say conditions inside the state’s prison facilities are extremely grim.\u003cimg src=\"https://external.fapa1-1.fna.fbcdn.net/safe_image.php?d=AQF1IAQxJNbWhoBY\u0026w=540\u0026h=282\u0026url=https%3A%2F%2Fi1.wp.com%2Fwp-cpr.s3.amazonaws.com%2Fuploads%2F2020%2F12%2F201214-DOC-CAMP-GEORGE-WEST-0002.jpg%3Fresize%3D1200%2C600\u0026cfs=1\u0026upscale=1\u0026fallback=news_d_placeholder_publisher\u0026_nc_cb=1\u0026_nc_hash=AQENGJ9nP12B-gko\" alt=\"\" width=\"500\" height=\"262\" caption=\"\" /\u003e\u003c/a\u003e\u003cp\u003ecpr.org\u003c/p\u003e\u003cp\u003e‘Of Course, It Feels Unsafe’: Colorado Prisons Face Staffing Crisis As Hundreds Of Guards, Inmates Sickened\u003c/p\u003eParole officers, correctional officers and advocates and families of inmates say conditions inside the state’s prison facilities are extremely grim.\u003ca href=\"https://www.cpr.org/2020/12/17/of-course-it-feels-unsafe-colorado-prisons-face-staffing-crisis-as-hundreds-of-guards-inmates-sickened/\"\u003eParole officers, correctional officers and advocates and families of inmates say conditions inside the state’s prison facilities are extremely grim.\u003c/a\u003e",
      "date_published": "2020-12-17T13:21:47-07:00",
      "date_modified": "2020-12-17T13:21:47-07:00",
      "author": {
        "name": "Colorado Attorneys Against Police Violence"
      }
    },
    {
      "id": "https://www.facebook.com/194372722325070",
      "url": "https://www.facebook.com/194372722325070",
      "title": "https://www.denverpost.com/…/elijah-mcclain-death-investig…/",
      "content_html": "\u003ca href=\"https://www.facebook.com/Colorado-Attorneys-Against-Police-Violence-106087521153591/\"\u003e\u003cimg src=\"https://scontent.fapa1-1.fna.fbcdn.net/v/t1.0-1/cp0/c23.0.50.50a/p50x50/118569704_145892603839749_1971037107782593743_n.png?_nc_cat=108\u0026ccb=2\u0026_nc_sid=dbb9e7\u0026_nc_ohc=m3os2-uLM0MAX_OEXRa\u0026_nc_ht=scontent.fapa1-1.fna\u0026_nc_tp=30\u0026oh=052ffa638da2b30bbb6033dbbd5bec94\u0026oe=6013C7AF\" alt=\"\" /\u003e\u003c/a\u003e\u003ca href=\"https://www.facebook.com/Colorado-Attorneys-Against-Police-Violence-106087521153591/\"\u003eColorado Attorneys Against Police Violence\u003c/a\u003e\u003ca href=\"https://www.facebook.com/permalink.php\"\u003e\u003c/a\u003e\u003ci\u003e\u003c/i\u003e\u003cp\u003e\u003ca href=\"https://www.denverpost.com/2020/12/17/elijah-mcclain-death-investigation-adams-county-coroner/\"\u003ehttps://www.denverpost.com/…/elijah-mcclain-death-investig…/\u003c/a\u003e\u003c/p\u003e\u003ca href=\"https://www.denverpost.com/2020/12/17/elijah-mcclain-death-investigation-adams-county-coroner/\"\u003eThe Adams County coroner has told Broomfield County that her office will no longer provide services to its neighbor starting Jan. 1, the result of an apparent rift over questions elected officials …\u003cimg src=\"https://external.fapa1-1.fna.fbcdn.net/safe_image.php?d=AQHzIXY62g95MIAh\u0026w=540\u0026h=282\u0026url=https%3A%2F%2Fwww.denverpost.com%2Fwp-content%2Fuploads%2F2020%2F06%2FTDP-L-ElijahMcClainmural062520-cha-357.jpg%3Fw%3D1024%26h%3D683\u0026cfs=1\u0026upscale=1\u0026fallback=news_d_placeholder_publisher\u0026_nc_cb=1\u0026_nc_hash=AQEpQqokXMGmSoBv\" alt=\"\" width=\"500\" height=\"262\" caption=\"\" /\u003e\u003c/a\u003e\u003cp\u003edenverpost.com\u003c/p\u003e\u003cp\u003eAdams County coroner severs ties with Broomfield after questions raised over handling of Elijah McClain death investigation\u003c/p\u003eThe Adams County coroner has told Broomfield County that her office will no longer provide services to its neighbor starting Jan. 1, the result of an apparent rift over questions elected officials …\u003ca href=\"https://www.denverpost.com/2020/12/17/elijah-mcclain-death-investigation-adams-county-coroner/\"\u003eThe Adams County coroner has told Broomfield County that her office will no longer provide services to its neighbor starting Jan. 1, the result of an apparent rift over questions elected officials …\u003c/a\u003e",
      "date_published": "2020-12-17T11:22:20-07:00",
      "date_modified": "2020-12-17T11:22:20-07:00",
      "author": {
        "name": "Colorado Attorneys Against Police Violence"
      }
    },
    {
      "id": "https://www.facebook.com/192969612465381",
      "url": "https://www.facebook.com/192969612465381",
      "title": "...",
      "content_html": "\u003ca href=\"https://www.facebook.com/Colorado-Attorneys-Against-Police-Violence-106087521153591/\"\u003e\u003cimg src=\"https://scontent.fapa1-1.fna.fbcdn.net/v/t1.0-1/cp0/c23.0.50.50a/p50x50/118569704_145892603839749_1971037107782593743_n.png?_nc_cat=108\u0026ccb=2\u0026_nc_sid=dbb9e7\u0026_nc_ohc=m3os2-uLM0MAX_OEXRa\u0026_nc_ht=scontent.fapa1-1.fna\u0026_nc_tp=30\u0026oh=052ffa638da2b30bbb6033dbbd5bec94\u0026oe=6013C7AF\" alt=\"\" /\u003e\u003c/a\u003e\u003ca href=\"https://www.facebook.com/Colorado-Attorneys-Against-Police-Violence-106087521153591/\"\u003eColorado Attorneys Against Police Violence\u003c/a\u003e\u003ca href=\"https://www.facebook.com/permalink.php\"\u003e\u003c/a\u003e\u003ci\u003e\u003c/i\u003e\u003cp\u003e\u003ca href=\"https://denverite.com/2020/12/14/how-denver-police-officers-secured-a-nearly-3-raise-even-though-city-council-didnt-want-to-give-them-one/?fbclid=IwAR2nSlWQ_EgkWgp6Pd4guVYLTieKsRcFDzTQILSE7jpvW7FP5Ba_pqeOKVw\"\u003ehttps://denverite.com/…/how-denver-police-officers-secure…/…\u003c/a\u003e\u003c/p\u003e\u003ca href=\"https://denverite.com/2020/12/14/how-denver-police-officers-secured-a-nearly-3-raise-even-though-city-council-didnt-want-to-give-them-one/\"\u003eThe new contract passed 10 to 3.\u003cimg src=\"https://external.fapa1-1.fna.fbcdn.net/safe_image.php?d=AQGRg9ObSbQ6DI2V\u0026w=540\u0026h=282\u0026url=https%3A%2F%2Fi0.wp.com%2Fwp-denverite.s3.amazonaws.com%2Fwp-content%2Fuploads%2Fsites%2F4%2F2020%2F04%2F200422-CORONAVIRUS-COVIC-CITY-COUNCIL-ZOOM-MEETING-SOCIAL-DISTANCING.jpg%3Fresize%3D1200%252C630%26ssl%3D1\u0026cfs=1\u0026upscale=1\u0026fallback=news_d_placeholder_publisher\u0026_nc_cb=1\u0026_nc_hash=AQEJFpZWJNYiKYZ1\" alt=\"\" width=\"500\" height=\"262\" caption=\"\" /\u003e\u003c/a\u003e\u003cp\u003edenverite.com\u003c/p\u003e\u003cp\u003eHow Denver police officers secured a nearly 3% raise even though city council didn’t want to give them one\u003c/p\u003eThe new contract passed 10 to 3.\u003ca href=\"https://denverite.com/2020/12/14/how-denver-police-officers-secured-a-nearly-3-raise-even-though-city-council-didnt-want-to-give-them-one/\"\u003eThe new contract passed 10 to 3.\u003c/a\u003e",
      "date_published": "2020-12-15T11:29:06-07:00",
      "date_modified": "2020-12-15T11:29:06-07:00",
      "author": {
        "name": "Colorado Attorneys Against Police Violence"
      }
    },
    {
      "id": "https://www.facebook.com/192893185806357",
      "url": "https://www.facebook.com/192893185806357",
      "title": "...",
      "content_html": "\u003ca href=\"https://www.facebook.com/Colorado-Attorneys-Against-Police-Violence-106087521153591/\"\u003e\u003cimg src=\"https://scontent.fapa1-1.fna.fbcdn.net/v/t1.0-1/cp0/c23.0.50.50a/p50x50/118569704_145892603839749_1971037107782593743_n.png?_nc_cat=108\u0026ccb=2\u0026_nc_sid=dbb9e7\u0026_nc_ohc=m3os2-uLM0MAX_OEXRa\u0026_nc_ht=scontent.fapa1-1.fna\u0026_nc_tp=30\u0026oh=052ffa638da2b30bbb6033dbbd5bec94\u0026oe=6013C7AF\" alt=\"\" /\u003e\u003c/a\u003e\u003ca href=\"https://www.facebook.com/Colorado-Attorneys-Against-Police-Violence-106087521153591/\"\u003eColorado Attorneys Against Police Violence\u003c/a\u003e\u003ca href=\"https://www.facebook.com/permalink.php\"\u003e\u003c/a\u003e\u003ci\u003e\u003c/i\u003e\u003cp\u003e\u003ca href=\"https://www.washingtonpost.com/outlook/2020/12/14/trump-death-penalty-cruelty/?fbclid=IwAR2xNN6t2am4qe-d7pxJTdbM33nM9JPW6XRb3zS6kSv9bu0qnwOUlmQU0kY\"\u003ehttps://www.washingtonpost.com/…/trump-death-penalty-crue…/…\u003c/a\u003e\u003c/p\u003e\u003ca href=\"https://www.washingtonpost.com/outlook/2020/12/14/trump-death-penalty-cruelty/\"\u003eNothing prepared me for the cruelty of this government's execution spree in its waning days.\u003cimg src=\"https://external.fapa1-1.fna.fbcdn.net/safe_image.php?d=AQHD-r3ZhKNaYQKb\u0026w=540\u0026h=282\u0026url=https%3A%2F%2Fwww.washingtonpost.com%2Fwp-apps%2Fimrs.php%3Fsrc%3Dhttps%3A%2F%2Farc-anglerfish-washpost-prod-washpost.s3.amazonaws.com%2Fpublic%2F2ZTKE4R55QI6XNMLCYR7MJTZMA.jpg%26w%3D1440\u0026cfs=1\u0026upscale=1\u0026fallback=news_d_placeholder_publisher\u0026_nc_cb=1\u0026_nc_hash=AQF1rvR1VIS2lBUF\" alt=\"\" width=\"500\" height=\"262\" caption=\"\" /\u003e\u003c/a\u003e\u003cp\u003ewashingtonpost.com\u003c/p\u003e\u003cp\u003ePerspective | My client atoned for his sin. The Trump administration had him killed anyway.\u003c/p\u003eNothing prepared me for the cruelty of this government's execution spree in its waning days.\u003ca href=\"https://www.washingtonpost.com/outlook/2020/12/14/trump-death-penalty-cruelty/\"\u003eNothing prepared me for the cruelty of this government's execution spree in its waning days.\u003c/a\u003e",
      "date_published": "2020-12-15T08:57:42-07:00",
      "date_modified": "2020-12-15T08:57:42-07:00",
      "author": {
        "name": "Colorado Attorneys Against Police Violence"
      }
    }
  ]
}
